LICENSE
LICENSE.txt
README.md
setup.cfg
setup.py
tuoni/TuoniAgent.py
tuoni/TuoniAlias.py
tuoni/TuoniC2.py
tuoni/TuoniCommand.py
tuoni/TuoniCommandPlugin.py
tuoni/TuoniCommandTemplate.py
tuoni/TuoniDataCredential.py
tuoni/TuoniDataHost.py
tuoni/TuoniDataService.py
tuoni/TuoniDefaultCommands.py
tuoni/TuoniEvent.py
tuoni/TuoniExceptions.py
tuoni/TuoniFile.py
tuoni/TuoniJob.py
tuoni/TuoniListener.py
tuoni/TuoniListenerPlugin.py
tuoni/TuoniPayloadPlugin.py
tuoni/TuoniResult.py
tuoni/TuoniResultPart.py
tuoni/TuoniUser.py
tuoni/__init__.py
tuoni.egg-info/PKG-INFO
tuoni.egg-info/SOURCES.txt
tuoni.egg-info/dependency_links.txt
tuoni.egg-info/requires.txt
tuoni.egg-info/top_level.txt